con_ACP/__init__.py
con_ACP/inf.py
con_ACP/model/ResNet.py
con_ACP/model/__init__.py
con_ACP/model/attention_encoder.py
con_ACP/model/cnn.py
con_ACP/model/lstm.py
con_ACP/model_old/ResNet.py
con_ACP/model_old/__init__.py
con_ACP/model_old/attention_encoder.py
con_ACP/model_old/cnn.py
con_ACP/model_old/lstm.py
fp_pred-0.0.1.dist-info/METADATA
fp_pred-0.0.1.dist-info/WHEEL
fp_pred-0.0.1.dist-info/top_level.txt
fp_pred-0.0.1.dist-info/RECORD
